singlora/__init__.py
singlora/main.py
singlora-0.0.1.dist-info/LICENSE
singlora-0.0.1.dist-info/METADATA
singlora-0.0.1.dist-info/WHEEL
singlora-0.0.1.dist-info/RECORD
